datafirst/__init__.py
datafirst/constants.py
datafirst/database.py
datafirst/models/database.py
datafirst/py.typed
datafirst/utils.py
datafirst-0.1.5.dist-info/LICENSE
datafirst-0.1.5.dist-info/METADATA
datafirst-0.1.5.dist-info/WHEEL
datafirst-0.1.5.dist-info/RECORD
