Metadata-Version: 2.1
Name: datafirst
Version: 0.1.5
Summary: A Python package for working with DataFirst database.
Home-page: https://github.com/ckids_datafirst/datafirst
License: MIT
Author: ckids-datafirst
Author-email: maxiosorio@gmail.com
Requires-Python: >=3.9.17,<4.0.0
Classifier: Development Status :: 3 - Alpha
Classifier: Intended Audience :: Developers
Classifier: License :: OSI Approved :: MIT License
Classifier: Operating System :: OS Independent
Classifier: Programming Language :: Python :: 3
Classifier: Programming Language :: Python :: 3.10
Classifier: Programming Language :: Python :: 3.11
Classifier: Programming Language :: Python :: 3.12
Classifier: Programming Language :: Python :: 3.9
Classifier: Topic :: Software Development :: Libraries :: Python Modules
Requires-Dist: dataclass-wizard (>=0.22.2,<0.23.0)
Project-URL: Repository, https://github.com/ckids_datafirst/datafirst
